cbpa/__init__.py
cbpa/gunicorn_config.py
cbpa/logger.py
cbpa/main.py
cbpa/schemas/__init__.py
cbpa/schemas/account.py
cbpa/schemas/alert.py
cbpa/schemas/api.py
cbpa/schemas/buy.py
cbpa/schemas/config.py
cbpa/schemas/currency.py
cbpa/schemas/health.py
cbpa/services/__init__.py
cbpa/services/account.py
cbpa/services/buy.py
cbpa/services/config.py
cbpa/services/discord.py
cbpa-0.1.1.dist-info/entry_points.txt
cbpa-0.1.1.dist-info/LICENSE
cbpa-0.1.1.dist-info/WHEEL
cbpa-0.1.1.dist-info/METADATA
cbpa-0.1.1.dist-info/RECORD
